denorm/__init__.py
denorm/apps.py
denorm/contextmanagers.py
denorm/denorms.py
denorm/dependencies.py
denorm/fields.py
denorm/helpers.py
denorm/middleware.py
denorm/models.py
denorm/tasks.py
denorm/conf/__init__.py
denorm/conf/settings.py
denorm/db/__init__.py
denorm/db/base.py
denorm/db/const.py
denorm/db/triggers.py
denorm/management/__init__.py
denorm/management/commands/__init__.py
denorm/management/commands/denorm_drop.py
denorm/management/commands/denorm_flush.py
denorm/management/commands/denorm_flush_via_queue.py
denorm/management/commands/denorm_init.py
denorm/management/commands/denorm_queue.py
denorm/management/commands/denorm_rebuild.py
denorm/management/commands/denorm_rebuild_triggers.py
denorm/management/commands/denorm_show_dirtyinstances_count.py
denorm/management/commands/denorm_sql.py
denorm/migrations/0001_initial.py
denorm/migrations/0001_squashed_0012_alter_dirtyinstance_object_id.py
denorm/migrations/0002_dirtyinstance_func_name.py
denorm/migrations/0003_auto_20211002_1955.py
denorm/migrations/0004_alter_dirtyinstance_success.py
denorm/migrations/0005_dirtyinstance_created_on.py
denorm/migrations/0006_auto_20211003_0346.py
denorm/migrations/0007_auto_created_on_now.py
denorm/migrations/0008_alter_dirtyinstance_object_id.py
denorm/migrations/0009_alter_dirtyinstance_object_id.py
denorm/migrations/0010_alter_dirtyinstance_object_id.py
denorm/migrations/0011_alter_dirtyinstance_object_id.py
denorm/migrations/0012_alter_dirtyinstance_object_id.py
denorm/migrations/0013_alter_dirtyinstance_success.py
denorm/migrations/0014_parametrized_notify.py
denorm/migrations/0015_remove_dirtyinstance_processing_finished_and_more.py
denorm/migrations/0016_not_parametrized_notify.py
denorm/migrations/__init__.py
django_denorm_iplweb-1.10.0.dist-info/licenses/AUTHORS.txt
django_denorm_iplweb-1.10.0.dist-info/licenses/LICENSE
django_denorm_iplweb-1.10.0.dist-info/METADATA
django_denorm_iplweb-1.10.0.dist-info/WHEEL
django_denorm_iplweb-1.10.0.dist-info/top_level.txt
django_denorm_iplweb-1.10.0.dist-info/RECORD
