Metadata-Version: 2.4
Name: django-denorm-iplweb
Version: 1.10.0
Summary: Denormalization magic for Django
Home-page: http://github.com/mpasternak/django-denorm-iplweb/
Author-email: michal.dtz@gmail.com
Classifier: Development Status :: 2 - Pre-Alpha
Classifier: Framework :: Django
Classifier: Intended Audience :: Developers
Classifier: Intended Audience :: System Administrators
Classifier: Operating System :: OS Independent
Classifier: Topic :: Software Development
License-File: LICENSE
License-File: AUTHORS.txt
Dynamic: author-email
Dynamic: classifier
Dynamic: description
Dynamic: home-page
Dynamic: license-file
Dynamic: summary
